Metadata-Version: 1.1
Name: micomplete
Version: 1.1.1
Summary: Quality control of assembled genomes
Home-page: https://bitbucket.org/evolegiolab/micomplete
Author: Eric Hugoson
Author-email: eric@hugoson.org
License: GNU General Public License v3 or later (G  PLv3+)
Keywords: bioinformatics completeness metagenomics
Platform: UNKNOWN
Classifier: Development Status :: 5 - Production/Stable
Classifier: Intended Audience :: Science/Research
Classifier: Topic :: Scientific/Engineering :: Bio-Informatics
Classifier: Environment :: Console
Classifier: License :: OSI Approved :: GNU General Public License v3 or later (GPLv3+)
Classifier: Programming Language :: Python :: 3
Classifier: Programming Language :: Python :: 3.5
Classifier: Programming Language :: Python :: 3.6
Classifier: Programming Language :: Python :: 3.7
